flaskcommand
