Metadata-Version: 1.1
Name: flask-command
Version: 0.0.3
Summary: flask-command - Run you flask+gunicorn app as a command
Home-page: https://github.com/ravenac95/flask-command
Author: Reuven V. Gonzales
Author-email: reuven@tobetter.us
License: MIT
Platform: *nix
Classifier: License :: OSI Approved :: MIT License
Classifier: Intended Audience :: Developers
Classifier: Programming Language :: Python
Classifier: Topic :: Internet :: WWW/HTTP :: WSGI :: Application
